stochasticclock/__init__.py
stochasticclock/clockprocesses.py
stochasticclock-0.0.3.dist-info/METADATA
stochasticclock-0.0.3.dist-info/WHEEL
stochasticclock-0.0.3.dist-info/licenses/LICENSE
stochasticclock-0.0.3.dist-info/RECORD
