Metadata-Version: 2.1
Name: stochasticclock
Version: 0.0.3
Summary: Atomic clock simulation
Project-URL: Homepage, https://github.com/Mitrxs/Stochastic-clock
Project-URL: Bug Tracker, https://github.com/Mitrxs/Stochastic-clock/issues
Project-URL: Changelog, https://github.com/Mitrxs/Stochastic-clock/blob/main/CHANGELOG.md
Author-email: Ali Sherzad <ali.sherzad@spc.ox.ac.uk>, Pranav Singh <ps2106@bath.ac.uk>
Maintainer-email: Ali Sherzad <ali.sherzad@spc.ox.ac.uk>
License: MIT
License-File: LICENSE
Keywords: Caesium,Metrology,SDE,atomic,clock,stochastic,timer
Classifier: License :: OSI Approved :: MIT License
Classifier: Operating System :: OS Independent
Classifier: Programming Language :: Python :: 3
Classifier: Topic :: Scientific/Engineering :: Physics
Requires-Python: >=3.8
Requires-Dist: numpy>=1.21.0
